baats/__init__.py
baats/baats.py
baats-0.1.0.dist-info/LICENSE
baats-0.1.0.dist-info/METADATA
baats-0.1.0.dist-info/WHEEL
baats-0.1.0.dist-info/top_level.txt
baats-0.1.0.dist-info/RECORD
