Metadata-Version: 2.1
Name: baats
Version: 0.1.0
Summary: Una librería para esconder cosas en archivos.
Home-page: https://github.com/Carlos-dev-G/baats
Author: Carlos-dev-G
Author-email: baa4tsdev@example.com
Classifier: Programming Language :: Python :: 3
Classifier: License :: OSI Approved :: MIT License
Classifier: Operating System :: OS Independent
Requires-Python: >=3.6
License-File: LICENSE
